<soap:Envelope xmlns:soap="http://schemas.xmlsoap.org/soap/envelope/"><soap:Body><ns3:getAllAtomicServicesResponse xmlns:ns2="http://www.ssw.pwr.wroc.pl/sdbeta" xmlns:ns3="http://mediator.atomic.platel.pwr.wroc.pl/"><ServiceDescriptionArray><ns2:serviceDescription><ns2:physicalDescription><ns2:serviceName>Odejmowanie</ns2:serviceName><ns2:serviceGlobalID>http://www.math.pwr.wroc.pl/math/odejmowanie</ns2:serviceGlobalID><ns2:address>http://156.17.130.39:10000/simpleMathSub?wsdl</ns2:address><ns2:operation>sub</ns2:operation></ns2:physicalDescription><ns2:functionalDescription><ns2:serviceClasses><ns2:serviceClass>odejmowanie</ns2:serviceClass></ns2:serviceClasses><ns2:description>Usługa odejmująca jedną liczbę od drugiej</ns2:description><ns2:metaKeywords><ns2:metaKeyword>odejmowanie</ns2:metaKeyword></ns2:metaKeywords><ns2:inputs><ns2:input><ns2:id>odjemna</ns2:id><ns2:label>Odjemna</ns2:label><ns2:dataType>Int</ns2:dataType><ns2:class>Odjemna</ns2:class><ns2:properties/></ns2:input><ns2:input><ns2:id>odjemnik</ns2:id><ns2:label>Odjemnik</ns2:label><ns2:dataType>Int</ns2:dataType><ns2:class>Odjemnik</ns2:class><ns2:properties/></ns2:input></ns2:inputs><ns2:outputs><ns2:output><ns2:id>roznica</ns2:id><ns2:label>Roznica</ns2:label><ns2:dataType>Int</ns2:dataType><ns2:class>Roznica</ns2:class><ns2:properties/></ns2:output></ns2:outputs><ns2:preconditions/><ns2:effects/></ns2:functionalDescription><ns2:nonFunctionalDescription><ns2:nonFunctionaleProperty><ns2:name>cost</ns2:name><ns2:value>1</ns2:value><ns2:unit>$</ns2:unit><ns2:relation>eq</ns2:relation></ns2:nonFunctionaleProperty></ns2:nonFunctionalDescription></ns2:serviceDescription><ns2:serviceDescription><ns2:physicalDescription><ns2:serviceName>Dodawanie</ns2:serviceName><ns2:serviceGlobalID>http://www.math.pwr.wroc.pl/math/dodawanie</ns2:serviceGlobalID><ns2:address>http://156.17.130.39:10000/simpleMathAdd?wsdl</ns2:address><ns2:operation>dodawanie</ns2:operation></ns2:physicalDescription><ns2:functionalDescription><ns2:serviceClasses><ns2:serviceClass>dodawanie</ns2:serviceClass></ns2:serviceClasses><ns2:description>Usługa dodająca dwie liczby</ns2:description><ns2:metaKeywords><ns2:metaKeyword>add</ns2:metaKeyword></ns2:metaKeywords><ns2:inputs><ns2:input><ns2:id>skladnik1</ns2:id><ns2:label>Skladnik</ns2:label><ns2:dataType>Int</ns2:dataType><ns2:class>Skladnik</ns2:class><ns2:properties/></ns2:input><ns2:input><ns2:id>skladnik2</ns2:id><ns2:label>Skladnik</ns2:label><ns2:dataType>Int</ns2:dataType><ns2:class>Skladnik</ns2:class><ns2:properties/></ns2:input></ns2:inputs><ns2:outputs><ns2:output><ns2:id>suma</ns2:id><ns2:label>Suma</ns2:label><ns2:dataType>Int</ns2:dataType><ns2:class>Suma</ns2:class><ns2:properties/></ns2:output></ns2:outputs><ns2:preconditions/><ns2:effects/></ns2:functionalDescription><ns2:nonFunctionalDescription><ns2:nonFunctionaleProperty><ns2:name>cost</ns2:name><ns2:value>1</ns2:value><ns2:unit>$</ns2:unit><ns2:relation>eq</ns2:relation></ns2:nonFunctionaleProperty></ns2:nonFunctionalDescription></ns2:serviceDescription><ns2:serviceDescription><ns2:physicalDescription><ns2:serviceName>Mnozenie</ns2:serviceName><ns2:serviceGlobalID>http://www.math.pwr.wroc.pl/math/mnozenie</ns2:serviceGlobalID><ns2:address>http://156.17.130.39:10000/simpleMathMul?wsdl</ns2:address><ns2:operation>mul</ns2:operation></ns2:physicalDescription><ns2:functionalDescription><ns2:serviceClasses><ns2:serviceClass>mnozenie</ns2:serviceClass></ns2:serviceClasses><ns2:description>Usługa mnożąca dwie liczby</ns2:description><ns2:metaKeywords><ns2:metaKeyword>mnożenie</ns2:metaKeyword></ns2:metaKeywords><ns2:inputs><ns2:input><ns2:id>czynnik1</ns2:id><ns2:label>Czynnik</ns2:label><ns2:dataType>Int</ns2:dataType><ns2:class>Czynnik</ns2:class><ns2:properties/></ns2:input><ns2:input><ns2:id>czynnik2</ns2:id><ns2:label>Czynnik</ns2:label><ns2:dataType>Int</ns2:dataType><ns2:class>Czynnik</ns2:class><ns2:properties/></ns2:input></ns2:inputs><ns2:outputs><ns2:output><ns2:id>iloczyn</ns2:id><ns2:label>iloczyn</ns2:label><ns2:dataType>Int</ns2:dataType><ns2:class>Iloczyn</ns2:class><ns2:properties/></ns2:output></ns2:outputs><ns2:preconditions/><ns2:effects/></ns2:functionalDescription><ns2:nonFunctionalDescription><ns2:nonFunctionaleProperty><ns2:name>cost</ns2:name><ns2:value>1</ns2:value><ns2:unit>$</ns2:unit><ns2:relation>eq</ns2:relation></ns2:nonFunctionaleProperty></ns2:nonFunctionalDescription></ns2:serviceDescription><ns2:serviceDescription><ns2:physicalDescription><ns2:serviceName>Dzielenie</ns2:serviceName><ns2:serviceGlobalID>http://www.math.pwr.wroc.pl/math/dzielenie</ns2:serviceGlobalID><ns2:address>http://156.17.130.39:10000/simpleMathDiv?wsdl</ns2:address><ns2:operation>div</ns2:operation></ns2:physicalDescription><ns2:functionalDescription><ns2:serviceClasses><ns2:serviceClass>dzielenie</ns2:serviceClass></ns2:serviceClasses><ns2:description>Usługa dzieląca jedną liczbę przez drugą</ns2:description><ns2:metaKeywords><ns2:metaKeyword>dzielenie</ns2:metaKeyword></ns2:metaKeywords><ns2:inputs><ns2:input><ns2:id>dzielna</ns2:id><ns2:label>dzielna</ns2:label><ns2:dataType>Int</ns2:dataType><ns2:class>Dzielna</ns2:class><ns2:properties/></ns2:input><ns2:input><ns2:id>dzielnik</ns2:id><ns2:label>Dzielnik</ns2:label><ns2:dataType>Int</ns2:dataType><ns2:class>Dzielnik</ns2:class><ns2:properties/></ns2:input></ns2:inputs><ns2:outputs><ns2:output><ns2:id>iloraz</ns2:id><ns2:label>Iloraz</ns2:label><ns2:dataType>Int</ns2:dataType><ns2:class>Iloraz</ns2:class><ns2:properties/></ns2:output></ns2:outputs><ns2:preconditions/><ns2:effects/></ns2:functionalDescription><ns2:nonFunctionalDescription><ns2:nonFunctionaleProperty><ns2:name>cost</ns2:name><ns2:value>1</ns2:value><ns2:unit>$</ns2:unit><ns2:relation>eq</ns2:relation></ns2:nonFunctionaleProperty></ns2:nonFunctionalDescription></ns2:serviceDescription><ns2:serviceDescription><ns2:physicalDescription><ns2:serviceName>Potegowanie</ns2:serviceName><ns2:serviceGlobalID>http://www.math.pwr.wroc.pl/math/potegowanie</ns2:serviceGlobalID><ns2:address>http://156.17.130.39:10000/simpleMathPow?wsdl</ns2:address><ns2:operation>pow</ns2:operation></ns2:physicalDescription><ns2:functionalDescription><ns2:serviceClasses><ns2:serviceClass>potegowanie</ns2:serviceClass></ns2:serviceClasses><ns2:description>Usługa podnoszaca liczbe do zadanej potegi</ns2:description><ns2:metaKeywords><ns2:metaKeyword>potegowanie</ns2:metaKeyword></ns2:metaKeywords><ns2:inputs><ns2:input><ns2:id>podstawa</ns2:id><ns2:label>Podstawa</ns2:label><ns2:dataType>Int</ns2:dataType><ns2:class>Podstawa</ns2:class><ns2:properties/></ns2:input><ns2:input><ns2:id>wykładnik</ns2:id><ns2:label>Wykładnik</ns2:label><ns2:dataType>Int</ns2:dataType><ns2:class>Wykładnik</ns2:class><ns2:properties/></ns2:input></ns2:inputs><ns2:outputs><ns2:output><ns2:id>potega</ns2:id><ns2:label>Potega</ns2:label><ns2:dataType>Int</ns2:dataType><ns2:class>Potega</ns2:class><ns2:properties/></ns2:output></ns2:outputs><ns2:preconditions/><ns2:effects/></ns2:functionalDescription><ns2:nonFunctionalDescription><ns2:nonFunctionaleProperty><ns2:name>cost</ns2:name><ns2:value>1</ns2:value><ns2:unit>$</ns2:unit><ns2:relation>eq</ns2:relation></ns2:nonFunctionaleProperty></ns2:nonFunctionalDescription></ns2:serviceDescription><ns2:serviceDescription><ns2:physicalDescription><ns2:serviceName>Odejmowanie</ns2:serviceName><ns2:serviceGlobalID>http://www.math.pwr.wroc.pl/math/odejmowanie</ns2:serviceGlobalID><ns2:address>http://156.17.130.39:10000/simpleMathSub?wsdl</ns2:address><ns2:operation>sub</ns2:operation></ns2:physicalDescription><ns2:functionalDescription><ns2:serviceClasses><ns2:serviceClass>odejmowanie</ns2:serviceClass></ns2:serviceClasses><ns2:description>Usługa odejmująca jedną liczbę od drugiej</ns2:description><ns2:metaKeywords><ns2:metaKeyword>odejmowanie</ns2:metaKeyword></ns2:metaKeywords><ns2:inputs><ns2:input><ns2:id>odjemna</ns2:id><ns2:label>Odjemna</ns2:label><ns2:dataType>Int</ns2:dataType><ns2:class>Odjemna</ns2:class><ns2:properties/></ns2:input><ns2:input><ns2:id>odjemnik</ns2:id><ns2:label>Odjemnik</ns2:label><ns2:dataType>Int</ns2:dataType><ns2:class>Odjemnik</ns2:class><ns2:properties/></ns2:input></ns2:inputs><ns2:outputs><ns2:output><ns2:id>roznica</ns2:id><ns2:label>Roznica</ns2:label><ns2:dataType>Int</ns2:dataType><ns2:class>Roznica</ns2:class><ns2:properties/></ns2:output></ns2:outputs><ns2:preconditions/><ns2:effects/></ns2:functionalDescription><ns2:nonFunctionalDescription><ns2:nonFunctionaleProperty><ns2:name>cost</ns2:name><ns2:value>1</ns2:value><ns2:unit>$</ns2:unit><ns2:relation>eq</ns2:relation></ns2:nonFunctionaleProperty></ns2:nonFunctionalDescription></ns2:serviceDescription><ns2:serviceDescription><ns2:physicalDescription><ns2:serviceName>Dodawanie</ns2:serviceName><ns2:serviceGlobalID>http://www.math.pwr.wroc.pl/math/dodawanie</ns2:serviceGlobalID><ns2:address>http://156.17.130.39:10000/simpleMathAdd?wsdl</ns2:address><ns2:operation>dodawanie</ns2:operation></ns2:physicalDescription><ns2:functionalDescription><ns2:serviceClasses><ns2:serviceClass>dodawanie</ns2:serviceClass></ns2:serviceClasses><ns2:description>Usługa dodająca dwie liczby</ns2:description><ns2:metaKeywords><ns2:metaKeyword>add</ns2:metaKeyword></ns2:metaKeywords><ns2:inputs><ns2:input><ns2:id>skladnik1</ns2:id><ns2:label>Skladnik</ns2:label><ns2:dataType>Int</ns2:dataType><ns2:class>Skladnik</ns2:class><ns2:properties/></ns2:input><ns2:input><ns2:id>skladnik2</ns2:id><ns2:label>Skladnik</ns2:label><ns2:dataType>Int</ns2:dataType><ns2:class>Skladnik</ns2:class><ns2:properties/></ns2:input></ns2:inputs><ns2:outputs><ns2:output><ns2:id>suma</ns2:id><ns2:label>Suma</ns2:label><ns2:dataType>Int</ns2:dataType><ns2:class>Suma</ns2:class><ns2:properties/></ns2:output></ns2:outputs><ns2:preconditions/><ns2:effects/></ns2:functionalDescription><ns2:nonFunctionalDescription><ns2:nonFunctionaleProperty><ns2:name>cost</ns2:name><ns2:value>1</ns2:value><ns2:unit>$</ns2:unit><ns2:relation>eq</ns2:relation></ns2:nonFunctionaleProperty></ns2:nonFunctionalDescription></ns2:serviceDescription><ns2:serviceDescription><ns2:physicalDescription><ns2:serviceName>Mnozenie</ns2:serviceName><ns2:serviceGlobalID>http://www.math.pwr.wroc.pl/math/mnozenie</ns2:serviceGlobalID><ns2:address>http://156.17.130.39:10000/simpleMathMul?wsdl</ns2:address><ns2:operation>mul</ns2:operation></ns2:physicalDescription><ns2:functionalDescription><ns2:serviceClasses><ns2:serviceClass>mnozenie</ns2:serviceClass></ns2:serviceClasses><ns2:description>Usługa mnożąca dwie liczby</ns2:description><ns2:metaKeywords><ns2:metaKeyword>mnożenie</ns2:metaKeyword></ns2:metaKeywords><ns2:inputs><ns2:input><ns2:id>czynnik1</ns2:id><ns2:label>Czynnik</ns2:label><ns2:dataType>Int</ns2:dataType><ns2:class>Czynnik</ns2:class><ns2:properties/></ns2:input><ns2:input><ns2:id>czynnik2</ns2:id><ns2:label>Czynnik</ns2:label><ns2:dataType>Int</ns2:dataType><ns2:class>Czynnik</ns2:class><ns2:properties/></ns2:input></ns2:inputs><ns2:outputs><ns2:output><ns2:id>iloczyn</ns2:id><ns2:label>iloczyn</ns2:label><ns2:dataType>Int</ns2:dataType><ns2:class>Iloczyn</ns2:class><ns2:properties/></ns2:output></ns2:outputs><ns2:preconditions/><ns2:effects/></ns2:functionalDescription><ns2:nonFunctionalDescription><ns2:nonFunctionaleProperty><ns2:name>cost</ns2:name><ns2:value>1</ns2:value><ns2:unit>$</ns2:unit><ns2:relation>eq</ns2:relation></ns2:nonFunctionaleProperty></ns2:nonFunctionalDescription></ns2:serviceDescription><ns2:serviceDescription><ns2:physicalDescription><ns2:serviceName>Dzielenie</ns2:serviceName><ns2:serviceGlobalID>http://www.math.pwr.wroc.pl/math/dzielenie</ns2:serviceGlobalID><ns2:address>http://156.17.130.39:10000/simpleMathDiv?wsdl</ns2:address><ns2:operation>div</ns2:operation></ns2:physicalDescription><ns2:functionalDescription><ns2:serviceClasses><ns2:serviceClass>dzielenie</ns2:serviceClass></ns2:serviceClasses><ns2:description>Usługa dzieląca jedną liczbę przez drugą</ns2:description><ns2:metaKeywords><ns2:metaKeyword>dzielenie</ns2:metaKeyword></ns2:metaKeywords><ns2:inputs><ns2:input><ns2:id>dzielna</ns2:id><ns2:label>dzielna</ns2:label><ns2:dataType>Int</ns2:dataType><ns2:class>Dzielna</ns2:class><ns2:properties/></ns2:input><ns2:input><ns2:id>dzielnik</ns2:id><ns2:label>Dzielnik</ns2:label><ns2:dataType>Int</ns2:dataType><ns2:class>Dzielnik</ns2:class><ns2:properties/></ns2:input></ns2:inputs><ns2:outputs><ns2:output><ns2:id>iloraz</ns2:id><ns2:label>Iloraz</ns2:label><ns2:dataType>Int</ns2:dataType><ns2:class>Iloraz</ns2:class><ns2:properties/></ns2:output></ns2:outputs><ns2:preconditions/><ns2:effects/></ns2:functionalDescription><ns2:nonFunctionalDescription><ns2:nonFunctionaleProperty><ns2:name>cost</ns2:name><ns2:value>1</ns2:value><ns2:unit>$</ns2:unit><ns2:relation>eq</ns2:relation></ns2:nonFunctionaleProperty></ns2:nonFunctionalDescription></ns2:serviceDescription><ns2:serviceDescription><ns2:physicalDescription><ns2:serviceName>Potegowanie</ns2:serviceName><ns2:serviceGlobalID>http://www.math.pwr.wroc.pl/math/potegowanie</ns2:serviceGlobalID><ns2:address>http://156.17.130.39:10000/simpleMathPow?wsdl</ns2:address><ns2:operation>pow</ns2:operation></ns2:physicalDescription><ns2:functionalDescription><ns2:serviceClasses><ns2:serviceClass>potegowanie</ns2:serviceClass></ns2:serviceClasses><ns2:description>Usługa podnoszaca liczbe do zadanej potegi</ns2:description><ns2:metaKeywords><ns2:metaKeyword>potegowanie</ns2:metaKeyword></ns2:metaKeywords><ns2:inputs><ns2:input><ns2:id>podstawa</ns2:id><ns2:label>Podstawa</ns2:label><ns2:dataType>Int</ns2:dataType><ns2:class>Podstawa</ns2:class><ns2:properties/></ns2:input><ns2:input><ns2:id>wykładnik</ns2:id><ns2:label>Wykładnik</ns2:label><ns2:dataType>Int</ns2:dataType><ns2:class>Wykładnik</ns2:class><ns2:properties/></ns2:input></ns2:inputs><ns2:outputs><ns2:output><ns2:id>potega</ns2:id><ns2:label>Potega</ns2:label><ns2:dataType>Int</ns2:dataType><ns2:class>Potega</ns2:class><ns2:properties/></ns2:output></ns2:outputs><ns2:preconditions/><ns2:effects/></ns2:functionalDescription><ns2:nonFunctionalDescription><ns2:nonFunctionaleProperty><ns2:name>cost</ns2:name><ns2:value>1</ns2:value><ns2:unit>$</ns2:unit><ns2:relation>eq</ns2:relation></ns2:nonFunctionaleProperty></ns2:nonFunctionalDescription></ns2:serviceDescription><ns2:serviceDescription><ns2:physicalDescription><ns2:serviceName>Odejmowanie</ns2:serviceName><ns2:serviceGlobalID>http://www.math.pwr.wroc.pl/math/odejmowanie</ns2:serviceGlobalID><ns2:address>http://156.17.130.39:10000/simpleMathSub?wsdl</ns2:address><ns2:operation>sub</ns2:operation></ns2:physicalDescription><ns2:functionalDescription><ns2:serviceClasses><ns2:serviceClass>odejmowanie</ns2:serviceClass></ns2:serviceClasses><ns2:description>Usługa odejmująca jedną liczbę od drugiej</ns2:description><ns2:metaKeywords><ns2:metaKeyword>odejmowanie</ns2:metaKeyword></ns2:metaKeywords><ns2:inputs><ns2:input><ns2:id>odjemna</ns2:id><ns2:label>Odjemna</ns2:label><ns2:dataType>Int</ns2:dataType><ns2:class>Odjemna</ns2:class><ns2:properties/></ns2:input><ns2:input><ns2:id>odjemnik</ns2:id><ns2:label>Odjemnik</ns2:label><ns2:dataType>Int</ns2:dataType><ns2:class>Odjemnik</ns2:class><ns2:properties/></ns2:input></ns2:inputs><ns2:outputs><ns2:output><ns2:id>roznica</ns2:id><ns2:label>Roznica</ns2:label><ns2:dataType>Int</ns2:dataType><ns2:class>Roznica</ns2:class><ns2:properties/></ns2:output></ns2:outputs><ns2:preconditions/><ns2:effects/></ns2:functionalDescription><ns2:nonFunctionalDescription><ns2:nonFunctionaleProperty><ns2:name>cost</ns2:name><ns2:value>1</ns2:value><ns2:unit>$</ns2:unit><ns2:relation>eq</ns2:relation></ns2:nonFunctionaleProperty></ns2:nonFunctionalDescription></ns2:serviceDescription><ns2:serviceDescription><ns2:physicalDescription><ns2:serviceName>Dodawanie</ns2:serviceName><ns2:serviceGlobalID>http://www.math.pwr.wroc.pl/math/dodawanie</ns2:serviceGlobalID><ns2:address>http://156.17.130.39:10000/simpleMathAdd?wsdl</ns2:address><ns2:operation>dodawanie</ns2:operation></ns2:physicalDescription><ns2:functionalDescription><ns2:serviceClasses><ns2:serviceClass>dodawanie</ns2:serviceClass></ns2:serviceClasses><ns2:description>Usługa dodająca dwie liczby</ns2:description><ns2:metaKeywords><ns2:metaKeyword>add</ns2:metaKeyword></ns2:metaKeywords><ns2:inputs><ns2:input><ns2:id>skladnik1</ns2:id><ns2:label>Skladnik</ns2:label><ns2:dataType>Int</ns2:dataType><ns2:class>Skladnik</ns2:class><ns2:properties/></ns2:input><ns2:input><ns2:id>skladnik2</ns2:id><ns2:label>Skladnik</ns2:label><ns2:dataType>Int</ns2:dataType><ns2:class>Skladnik</ns2:class><ns2:properties/></ns2:input></ns2:inputs><ns2:outputs><ns2:output><ns2:id>suma</ns2:id><ns2:label>Suma</ns2:label><ns2:dataType>Int</ns2:dataType><ns2:class>Suma</ns2:class><ns2:properties/></ns2:output></ns2:outputs><ns2:preconditions/><ns2:effects/></ns2:functionalDescription><ns2:nonFunctionalDescription><ns2:nonFunctionaleProperty><ns2:name>cost</ns2:name><ns2:value>1</ns2:value><ns2:unit>$</ns2:unit><ns2:relation>eq</ns2:relation></ns2:nonFunctionaleProperty></ns2:nonFunctionalDescription></ns2:serviceDescription><ns2:serviceDescription><ns2:physicalDescription><ns2:serviceName>Mnozenie</ns2:serviceName><ns2:serviceGlobalID>http://www.math.pwr.wroc.pl/math/mnozenie</ns2:serviceGlobalID><ns2:address>http://156.17.130.39:10000/simpleMathMul?wsdl</ns2:address><ns2:operation>mul</ns2:operation></ns2:physicalDescription><ns2:functionalDescription><ns2:serviceClasses><ns2:serviceClass>mnozenie</ns2:serviceClass></ns2:serviceClasses><ns2:description>Usługa mnożąca dwie liczby</ns2:description><ns2:metaKeywords><ns2:metaKeyword>mnożenie</ns2:metaKeyword></ns2:metaKeywords><ns2:inputs><ns2:input><ns2:id>czynnik1</ns2:id><ns2:label>Czynnik</ns2:label><ns2:dataType>Int</ns2:dataType><ns2:class>Czynnik</ns2:class><ns2:properties/></ns2:input><ns2:input><ns2:id>czynnik2</ns2:id><ns2:label>Czynnik</ns2:label><ns2:dataType>Int</ns2:dataType><ns2:class>Czynnik</ns2:class><ns2:properties/></ns2:input></ns2:inputs><ns2:outputs><ns2:output><ns2:id>iloczyn</ns2:id><ns2:label>iloczyn</ns2:label><ns2:dataType>Int</ns2:dataType><ns2:class>Iloczyn</ns2:class><ns2:properties/></ns2:output></ns2:outputs><ns2:preconditions/><ns2:effects/></ns2:functionalDescription><ns2:nonFunctionalDescription><ns2:nonFunctionaleProperty><ns2:name>cost</ns2:name><ns2:value>1</ns2:value><ns2:unit>$</ns2:unit><ns2:relation>eq</ns2:relation></ns2:nonFunctionaleProperty></ns2:nonFunctionalDescription></ns2:serviceDescription><ns2:serviceDescription><ns2:physicalDescription><ns2:serviceName>Dzielenie</ns2:serviceName><ns2:serviceGlobalID>http://www.math.pwr.wroc.pl/math/dzielenie</ns2:serviceGlobalID><ns2:address>http://156.17.130.39:10000/simpleMathDiv?wsdl</ns2:address><ns2:operation>div</ns2:operation></ns2:physicalDescription><ns2:functionalDescription><ns2:serviceClasses><ns2:serviceClass>dzielenie</ns2:serviceClass></ns2:serviceClasses><ns2:description>Usługa dzieląca jedną liczbę przez drugą</ns2:description><ns2:metaKeywords><ns2:metaKeyword>dzielenie</ns2:metaKeyword></ns2:metaKeywords><ns2:inputs><ns2:input><ns2:id>dzielna</ns2:id><ns2:label>dzielna</ns2:label><ns2:dataType>Int</ns2:dataType><ns2:class>Dzielna</ns2:class><ns2:properties/></ns2:input><ns2:input><ns2:id>dzielnik</ns2:id><ns2:label>Dzielnik</ns2:label><ns2:dataType>Int</ns2:dataType><ns2:class>Dzielnik</ns2:class><ns2:properties/></ns2:input></ns2:inputs><ns2:outputs><ns2:output><ns2:id>iloraz</ns2:id><ns2:label>Iloraz</ns2:label><ns2:dataType>Int</ns2:dataType><ns2:class>Iloraz</ns2:class><ns2:properties/></ns2:output></ns2:outputs><ns2:preconditions/><ns2:effects/></ns2:functionalDescription><ns2:nonFunctionalDescription><ns2:nonFunctionaleProperty><ns2:name>cost</ns2:name><ns2:value>1</ns2:value><ns2:unit>$</ns2:unit><ns2:relation>eq</ns2:relation></ns2:nonFunctionaleProperty></ns2:nonFunctionalDescription></ns2:serviceDescription><ns2:serviceDescription><ns2:physicalDescription><ns2:serviceName>Potegowanie</ns2:serviceName><ns2:serviceGlobalID>http://www.math.pwr.wroc.pl/math/potegowanie</ns2:serviceGlobalID><ns2:address>http://156.17.130.39:10000/simpleMathPow?wsdl</ns2:address><ns2:operation>pow</ns2:operation></ns2:physicalDescription><ns2:functionalDescription><ns2:serviceClasses><ns2:serviceClass>potegowanie</ns2:serviceClass></ns2:serviceClasses><ns2:description>Usługa podnoszaca liczbe do zadanej potegi</ns2:description><ns2:metaKeywords><ns2:metaKeyword>potegowanie</ns2:metaKeyword></ns2:metaKeywords><ns2:inputs><ns2:input><ns2:id>podstawa</ns2:id><ns2:label>Podstawa</ns2:label><ns2:dataType>Int</ns2:dataType><ns2:class>Podstawa</ns2:class><ns2:properties/></ns2:input><ns2:input><ns2:id>wykładnik</ns2:id><ns2:label>Wykładnik</ns2:label><ns2:dataType>Int</ns2:dataType><ns2:class>Wykładnik</ns2:class><ns2:properties/></ns2:input></ns2:inputs><ns2:outputs><ns2:output><ns2:id>potega</ns2:id><ns2:label>Potega</ns2:label><ns2:dataType>Int</ns2:dataType><ns2:class>Potega</ns2:class><ns2:properties/></ns2:output></ns2:outputs><ns2:preconditions/><ns2:effects/></ns2:functionalDescription><ns2:nonFunctionalDescription><ns2:nonFunctionaleProperty><ns2:name>cost</ns2:name><ns2:value>1</ns2:value><ns2:unit>$</ns2:unit><ns2:relation>eq</ns2:relation></ns2:nonFunctionaleProperty></ns2:nonFunctionalDescription></ns2:serviceDescription><ns2:serviceDescription><ns2:physicalDescription><ns2:serviceName>Odejmowanie</ns2:serviceName><ns2:serviceGlobalID>http://www.math.pwr.wroc.pl/math/odejmowanie</ns2:serviceGlobalID><ns2:address>http://156.17.130.39:10000/simpleMathSub?wsdl</ns2:address><ns2:operation>sub</ns2:operation></ns2:physicalDescription><ns2:functionalDescription><ns2:serviceClasses><ns2:serviceClass>odejmowanie</ns2:serviceClass></ns2:serviceClasses><ns2:description>Usługa odejmująca jedną liczbę od drugiej</ns2:description><ns2:metaKeywords><ns2:metaKeyword>odejmowanie</ns2:metaKeyword></ns2:metaKeywords><ns2:inputs><ns2:input><ns2:id>odjemna</ns2:id><ns2:label>Odjemna</ns2:label><ns2:dataType>Int</ns2:dataType><ns2:class>Odjemna</ns2:class><ns2:properties/></ns2:input><ns2:input><ns2:id>odjemnik</ns2:id><ns2:label>Odjemnik</ns2:label><ns2:dataType>Int</ns2:dataType><ns2:class>Odjemnik</ns2:class><ns2:properties/></ns2:input></ns2:inputs><ns2:outputs><ns2:output><ns2:id>roznica</ns2:id><ns2:label>Roznica</ns2:label><ns2:dataType>Int</ns2:dataType><ns2:class>Roznica</ns2:class><ns2:properties/></ns2:output></ns2:outputs><ns2:preconditions/><ns2:effects/></ns2:functionalDescription><ns2:nonFunctionalDescription><ns2:nonFunctionaleProperty><ns2:name>cost</ns2:name><ns2:value>1</ns2:value><ns2:unit>$</ns2:unit><ns2:relation>eq</ns2:relation></ns2:nonFunctionaleProperty></ns2:nonFunctionalDescription></ns2:serviceDescription><ns2:serviceDescription><ns2:physicalDescription><ns2:serviceName>Dodawanie</ns2:serviceName><ns2:serviceGlobalID>http://www.math.pwr.wroc.pl/math/dodawanie</ns2:serviceGlobalID><ns2:address>http://156.17.130.39:10000/simpleMathAdd?wsdl</ns2:address><ns2:operation>dodawanie</ns2:operation></ns2:physicalDescription><ns2:functionalDescription><ns2:serviceClasses><ns2:serviceClass>dodawanie</ns2:serviceClass></ns2:serviceClasses><ns2:description>Usługa dodająca dwie liczby</ns2:description><ns2:metaKeywords><ns2:metaKeyword>add</ns2:metaKeyword></ns2:metaKeywords><ns2:inputs><ns2:input><ns2:id>skladnik1</ns2:id><ns2:label>Skladnik</ns2:label><ns2:dataType>Int</ns2:dataType><ns2:class>Skladnik</ns2:class><ns2:properties/></ns2:input><ns2:input><ns2:id>skladnik2</ns2:id><ns2:label>Skladnik</ns2:label><ns2:dataType>Int</ns2:dataType><ns2:class>Skladnik</ns2:class><ns2:properties/></ns2:input></ns2:inputs><ns2:outputs><ns2:output><ns2:id>suma</ns2:id><ns2:label>Suma</ns2:label><ns2:dataType>Int</ns2:dataType><ns2:class>Suma</ns2:class><ns2:properties/></ns2:output></ns2:outputs><ns2:preconditions/><ns2:effects/></ns2:functionalDescription><ns2:nonFunctionalDescription><ns2:nonFunctionaleProperty><ns2:name>cost</ns2:name><ns2:value>1</ns2:value><ns2:unit>$</ns2:unit><ns2:relation>eq</ns2:relation></ns2:nonFunctionaleProperty></ns2:nonFunctionalDescription></ns2:serviceDescription><ns2:serviceDescription><ns2:physicalDescription><ns2:serviceName>Mnozenie</ns2:serviceName><ns2:serviceGlobalID>http://www.math.pwr.wroc.pl/math/mnozenie</ns2:serviceGlobalID><ns2:address>http://156.17.130.39:10000/simpleMathMul?wsdl</ns2:address><ns2:operation>mul</ns2:operation></ns2:physicalDescription><ns2:functionalDescription><ns2:serviceClasses><ns2:serviceClass>mnozenie</ns2:serviceClass></ns2:serviceClasses><ns2:description>Usługa mnożąca dwie liczby</ns2:description><ns2:metaKeywords><ns2:metaKeyword>mnożenie</ns2:metaKeyword></ns2:metaKeywords><ns2:inputs><ns2:input><ns2:id>czynnik1</ns2:id><ns2:label>Czynnik</ns2:label><ns2:dataType>Int</ns2:dataType><ns2:class>Czynnik</ns2:class><ns2:properties/></ns2:input><ns2:input><ns2:id>czynnik2</ns2:id><ns2:label>Czynnik</ns2:label><ns2:dataType>Int</ns2:dataType><ns2:class>Czynnik</ns2:class><ns2:properties/></ns2:input></ns2:inputs><ns2:outputs><ns2:output><ns2:id>iloczyn</ns2:id><ns2:label>iloczyn</ns2:label><ns2:dataType>Int</ns2:dataType><ns2:class>Iloczyn</ns2:class><ns2:properties/></ns2:output></ns2:outputs><ns2:preconditions/><ns2:effects/></ns2:functionalDescription><ns2:nonFunctionalDescription><ns2:nonFunctionaleProperty><ns2:name>cost</ns2:name><ns2:value>1</ns2:value><ns2:unit>$</ns2:unit><ns2:relation>eq</ns2:relation></ns2:nonFunctionaleProperty></ns2:nonFunctionalDescription></ns2:serviceDescription><ns2:serviceDescription><ns2:physicalDescription><ns2:serviceName>Dzielenie</ns2:serviceName><ns2:serviceGlobalID>http://www.math.pwr.wroc.pl/math/dzielenie</ns2:serviceGlobalID><ns2:address>http://156.17.130.39:10000/simpleMathDiv?wsdl</ns2:address><ns2:operation>div</ns2:operation></ns2:physicalDescription><ns2:functionalDescription><ns2:serviceClasses><ns2:serviceClass>dzielenie</ns2:serviceClass></ns2:serviceClasses><ns2:description>Usługa dzieląca jedną liczbę przez drugą</ns2:description><ns2:metaKeywords><ns2:metaKeyword>dzielenie</ns2:metaKeyword></ns2:metaKeywords><ns2:inputs><ns2:input><ns2:id>dzielna</ns2:id><ns2:label>dzielna</ns2:label><ns2:dataType>Int</ns2:dataType><ns2:class>Dzielna</ns2:class><ns2:properties/></ns2:input><ns2:input><ns2:id>dzielnik</ns2:id><ns2:label>Dzielnik</ns2:label><ns2:dataType>Int</ns2:dataType><ns2:class>Dzielnik</ns2:class><ns2:properties/></ns2:input></ns2:inputs><ns2:outputs><ns2:output><ns2:id>iloraz</ns2:id><ns2:label>Iloraz</ns2:label><ns2:dataType>Int</ns2:dataType><ns2:class>Iloraz</ns2:class><ns2:properties/></ns2:output></ns2:outputs><ns2:preconditions/><ns2:effects/></ns2:functionalDescription><ns2:nonFunctionalDescription><ns2:nonFunctionaleProperty><ns2:name>cost</ns2:name><ns2:value>1</ns2:value><ns2:unit>$</ns2:unit><ns2:relation>eq</ns2:relation></ns2:nonFunctionaleProperty></ns2:nonFunctionalDescription></ns2:serviceDescription><ns2:serviceDescription><ns2:physicalDescription><ns2:serviceName>Potegowanie</ns2:serviceName><ns2:serviceGlobalID>http://www.math.pwr.wroc.pl/math/potegowanie</ns2:serviceGlobalID><ns2:address>http://156.17.130.39:10000/simpleMathPow?wsdl</ns2:address><ns2:operation>pow</ns2:operation></ns2:physicalDescription><ns2:functionalDescription><ns2:serviceClasses><ns2:serviceClass>potegowanie</ns2:serviceClass></ns2:serviceClasses><ns2:description>Usługa podnoszaca liczbe do zadanej potegi</ns2:description><ns2:metaKeywords><ns2:metaKeyword>potegowanie</ns2:metaKeyword></ns2:metaKeywords><ns2:inputs><ns2:input><ns2:id>podstawa</ns2:id><ns2:label>Podstawa</ns2:label><ns2:dataType>Int</ns2:dataType><ns2:class>Podstawa</ns2:class><ns2:properties/></ns2:input><ns2:input><ns2:id>wykładnik</ns2:id><ns2:label>Wykładnik</ns2:label><ns2:dataType>Int</ns2:dataType><ns2:class>Wykładnik</ns2:class><ns2:properties/></ns2:input></ns2:inputs><ns2:outputs><ns2:output><ns2:id>potega</ns2:id><ns2:label>Potega</ns2:label><ns2:dataType>Int</ns2:dataType><ns2:class>Potega</ns2:class><ns2:properties/></ns2:output></ns2:outputs><ns2:preconditions/><ns2:effects/></ns2:functionalDescription><ns2:nonFunctionalDescription><ns2:nonFunctionaleProperty><ns2:name>cost</ns2:name><ns2:value>1</ns2:value><ns2:unit>$</ns2:unit><ns2:relation>eq</ns2:relation></ns2:nonFunctionaleProperty></ns2:nonFunctionalDescription></ns2:serviceDescription><ns2:serviceDescription><ns2:physicalDescription><ns2:serviceName>Odejmowanie</ns2:serviceName><ns2:serviceGlobalID>http://www.math.pwr.wroc.pl/math/odejmowanie</ns2:serviceGlobalID><ns2:address>http://156.17.130.39:10000/simpleMathSub?wsdl</ns2:address><ns2:operation>sub</ns2:operation></ns2:physicalDescription><ns2:functionalDescription><ns2:serviceClasses><ns2:serviceClass>odejmowanie</ns2:serviceClass></ns2:serviceClasses><ns2:description>Usługa odejmująca jedną liczbę od drugiej</ns2:description><ns2:metaKeywords><ns2:metaKeyword>odejmowanie</ns2:metaKeyword></ns2:metaKeywords><ns2:inputs><ns2:input><ns2:id>odjemna</ns2:id><ns2:label>Odjemna</ns2:label><ns2:dataType>Int</ns2:dataType><ns2:class>Odjemna</ns2:class><ns2:properties/></ns2:input><ns2:input><ns2:id>odjemnik</ns2:id><ns2:label>Odjemnik</ns2:label><ns2:dataType>Int</ns2:dataType><ns2:class>Odjemnik</ns2:class><ns2:properties/></ns2:input></ns2:inputs><ns2:outputs><ns2:output><ns2:id>roznica</ns2:id><ns2:label>Roznica</ns2:label><ns2:dataType>Int</ns2:dataType><ns2:class>Roznica</ns2:class><ns2:properties/></ns2:output></ns2:outputs><ns2:preconditions/><ns2:effects/></ns2:functionalDescription><ns2:nonFunctionalDescription><ns2:nonFunctionaleProperty><ns2:name>cost</ns2:name><ns2:value>1</ns2:value><ns2:unit>$</ns2:unit><ns2:relation>eq</ns2:relation></ns2:nonFunctionaleProperty></ns2:nonFunctionalDescription></ns2:serviceDescription><ns2:serviceDescription><ns2:physicalDescription><ns2:serviceName>Dodawanie</ns2:serviceName><ns2:serviceGlobalID>http://www.math.pwr.wroc.pl/math/dodawanie</ns2:serviceGlobalID><ns2:address>http://156.17.130.39:10000/simpleMathAdd?wsdl</ns2:address><ns2:operation>dodawanie</ns2:operation></ns2:physicalDescription><ns2:functionalDescription><ns2:serviceClasses><ns2:serviceClass>dodawanie</ns2:serviceClass></ns2:serviceClasses><ns2:description>Usługa dodająca dwie liczby</ns2:description><ns2:metaKeywords><ns2:metaKeyword>add</ns2:metaKeyword></ns2:metaKeywords><ns2:inputs><ns2:input><ns2:id>skladnik1</ns2:id><ns2:label>Skladnik</ns2:label><ns2:dataType>Int</ns2:dataType><ns2:class>Skladnik</ns2:class><ns2:properties/></ns2:input><ns2:input><ns2:id>skladnik2</ns2:id><ns2:label>Skladnik</ns2:label><ns2:dataType>Int</ns2:dataType><ns2:class>Skladnik</ns2:class><ns2:properties/></ns2:input></ns2:inputs><ns2:outputs><ns2:output><ns2:id>suma</ns2:id><ns2:label>Suma</ns2:label><ns2:dataType>Int</ns2:dataType><ns2:class>Suma</ns2:class><ns2:properties/></ns2:output></ns2:outputs><ns2:preconditions/><ns2:effects/></ns2:functionalDescription><ns2:nonFunctionalDescription><ns2:nonFunctionaleProperty><ns2:name>cost</ns2:name><ns2:value>1</ns2:value><ns2:unit>$</ns2:unit><ns2:relation>eq</ns2:relation></ns2:nonFunctionaleProperty></ns2:nonFunctionalDescription></ns2:serviceDescription><ns2:serviceDescription><ns2:physicalDescription><ns2:serviceName>Mnozenie</ns2:serviceName><ns2:serviceGlobalID>http://www.math.pwr.wroc.pl/math/mnozenie</ns2:serviceGlobalID><ns2:address>http://156.17.130.39:10000/simpleMathMul?wsdl</ns2:address><ns2:operation>mul</ns2:operation></ns2:physicalDescription><ns2:functionalDescription><ns2:serviceClasses><ns2:serviceClass>mnozenie</ns2:serviceClass></ns2:serviceClasses><ns2:description>Usługa mnożąca dwie liczby</ns2:description><ns2:metaKeywords><ns2:metaKeyword>mnożenie</ns2:metaKeyword></ns2:metaKeywords><ns2:inputs><ns2:input><ns2:id>czynnik1</ns2:id><ns2:label>Czynnik</ns2:label><ns2:dataType>Int</ns2:dataType><ns2:class>Czynnik</ns2:class><ns2:properties/></ns2:input><ns2:input><ns2:id>czynnik2</ns2:id><ns2:label>Czynnik</ns2:label><ns2:dataType>Int</ns2:dataType><ns2:class>Czynnik</ns2:class><ns2:properties/></ns2:input></ns2:inputs><ns2:outputs><ns2:output><ns2:id>iloczyn</ns2:id><ns2:label>iloczyn</ns2:label><ns2:dataType>Int</ns2:dataType><ns2:class>Iloczyn</ns2:class><ns2:properties/></ns2:output></ns2:outputs><ns2:preconditions/><ns2:effects/></ns2:functionalDescription><ns2:nonFunctionalDescription><ns2:nonFunctionaleProperty><ns2:name>cost</ns2:name><ns2:value>1</ns2:value><ns2:unit>$</ns2:unit><ns2:relation>eq</ns2:relation></ns2:nonFunctionaleProperty></ns2:nonFunctionalDescription></ns2:serviceDescription><ns2:serviceDescription><ns2:physicalDescription><ns2:serviceName>Dzielenie</ns2:serviceName><ns2:serviceGlobalID>http://www.math.pwr.wroc.pl/math/dzielenie</ns2:serviceGlobalID><ns2:address>http://156.17.130.39:10000/simpleMathDiv?wsdl</ns2:address><ns2:operation>div</ns2:operation></ns2:physicalDescription><ns2:functionalDescription><ns2:serviceClasses><ns2:serviceClass>dzielenie</ns2:serviceClass></ns2:serviceClasses><ns2:description>Usługa dzieląca jedną liczbę przez drugą</ns2:description><ns2:metaKeywords><ns2:metaKeyword>dzielenie</ns2:metaKeyword></ns2:metaKeywords><ns2:inputs><ns2:input><ns2:id>dzielna</ns2:id><ns2:label>dzielna</ns2:label><ns2:dataType>Int</ns2:dataType><ns2:class>Dzielna</ns2:class><ns2:properties/></ns2:input><ns2:input><ns2:id>dzielnik</ns2:id><ns2:label>Dzielnik</ns2:label><ns2:dataType>Int</ns2:dataType><ns2:class>Dzielnik</ns2:class><ns2:properties/></ns2:input></ns2:inputs><ns2:outputs><ns2:output><ns2:id>iloraz</ns2:id><ns2:label>Iloraz</ns2:label><ns2:dataType>Int</ns2:dataType><ns2:class>Iloraz</ns2:class><ns2:properties/></ns2:output></ns2:outputs><ns2:preconditions/><ns2:effects/></ns2:functionalDescription><ns2:nonFunctionalDescription><ns2:nonFunctionaleProperty><ns2:name>cost</ns2:name><ns2:value>1</ns2:value><ns2:unit>$</ns2:unit><ns2:relation>eq</ns2:relation></ns2:nonFunctionaleProperty></ns2:nonFunctionalDescription></ns2:serviceDescription><ns2:serviceDescription><ns2:physicalDescription><ns2:serviceName>Potegowanie</ns2:serviceName><ns2:serviceGlobalID>http://www.math.pwr.wroc.pl/math/potegowanie</ns2:serviceGlobalID><ns2:address>http://156.17.130.39:10000/simpleMathPow?wsdl</ns2:address><ns2:operation>pow</ns2:operation></ns2:physicalDescription><ns2:functionalDescription><ns2:serviceClasses><ns2:serviceClass>potegowanie</ns2:serviceClass></ns2:serviceClasses><ns2:description>Usługa podnoszaca liczbe do zadanej potegi</ns2:description><ns2:metaKeywords><ns2:metaKeyword>potegowanie</ns2:metaKeyword></ns2:metaKeywords><ns2:inputs><ns2:input><ns2:id>podstawa</ns2:id><ns2:label>Podstawa</ns2:label><ns2:dataType>Int</ns2:dataType><ns2:class>Podstawa</ns2:class><ns2:properties/></ns2:input><ns2:input><ns2:id>wykładnik</ns2:id><ns2:label>Wykładnik</ns2:label><ns2:dataType>Int</ns2:dataType><ns2:class>Wykładnik</ns2:class><ns2:properties/></ns2:input></ns2:inputs><ns2:outputs><ns2:output><ns2:id>potega</ns2:id><ns2:label>Potega</ns2:label><ns2:dataType>Int</ns2:dataType><ns2:class>Potega</ns2:class><ns2:properties/></ns2:output></ns2:outputs><ns2:preconditions/><ns2:effects/></ns2:functionalDescription><ns2:nonFunctionalDescription><ns2:nonFunctionaleProperty><ns2:name>cost</ns2:name><ns2:value>1</ns2:value><ns2:unit>$</ns2:unit><ns2:relation>eq</ns2:relation></ns2:nonFunctionaleProperty></ns2:nonFunctionalDescription></ns2:serviceDescription></ServiceDescriptionArray></ns3:getAllAtomicServicesResponse></soap:Body></soap:Envelope>